rtl/output_mac.v
`timescale 1ns/1ps

module output_mac #(
    parameter N = 2,                // number of tokens
    parameter D = 4                 // embedding dimension
)(
    input  wire                         clk,
    input  wire                         start,

    input  signed [31:0] W   [0:N-1][0:N-1],   // softmax weights  Q8.8
    input  signed [31:0] V   [0:N-1][0:D-1],   // value matrix     integer

    output reg signed [31:0] OUT [0:N-1][0:D-1],
    output reg                          done
);

    integer i, j, k;

    // 64-bit accumulator to hold W*V before rescaling
    // W is 32-bit, V is 32-bit → product is up to 64-bit
    reg signed [63:0] acc;

    always @(posedge clk) begin

        if (start) begin

            for (i = 0; i < N; i = i + 1) begin
                for (j = 0; j < D; j = j + 1) begin

                    // ── accumulate W[i][k] × V[k][j] ──────────
                    acc = 64'sd0;
                    for (k = 0; k < N; k = k + 1)
                        acc = acc + $signed(W[i][k]) * $signed(V[k][j]);
                    OUT[i][j] <= acc >>> 8;

                end
            end

            done <= 1'b1;

        end else begin
            done <= 1'b0;
        end

    end

endmodule

rtl/softmax_approx.v
`timescale 1ns/1ps

module softmax_approx #(
    parameter N = 2                 // number of tokens
)(
    input  wire                          clk,
    input  wire                          start,
    input  signed [31:0]  SCALE  [0:N-1][0:N-1],
    output reg   signed [31:0]  WEIGHT [0:N-1][0:N-1],
    output reg                           done
);

    // ── loop indices ───────────────────────────────────────────
    integer i, j;

    // ── per-row temporaries (module-level regs) ────────────────
    reg signed [31:0] max_val;
    reg signed [31:0] shifted  [0:N-1];  
    reg        [31:0] exp_val  [0:N-1]; 
    reg        [63:0] sum_exp;           

    function [31:0] exp_lut;
        input signed [31:0] x;
        reg [31:0] abs_x;
        begin
            if (x >= 0) begin
                exp_lut = 32'd256;          // exp(0) = 1.0
            end else begin
                abs_x = -x;                 // magnitude of negative x
                if      (abs_x == 32'd1)  exp_lut = 32'd94;
                else if (abs_x == 32'd2)  exp_lut = 32'd35;
                else if (abs_x == 32'd3)  exp_lut = 32'd13;
                else if (abs_x == 32'd4)  exp_lut = 32'd5;
                else if (abs_x == 32'd5)  exp_lut = 32'd2;
                else if (abs_x == 32'd6)  exp_lut = 32'd1;
                else                      exp_lut = 32'd0;  // exp(−7+) ≈ 0
            end
        end
    endfunction

    // ── main FSM ───────────────────────────────────────────────
    always @(posedge clk) begin

        if (start) begin

            for (i = 0; i < N; i = i + 1) begin

                // ── STEP 1 : find row maximum ──────────────────
                max_val = SCALE[i][0];
                for (j = 1; j < N; j = j + 1)
                    if (SCALE[i][j] > max_val)
                        max_val = SCALE[i][j];

                // ── STEP 2 : subtract max, apply exp LUT ───────
                sum_exp = 64'd0;
                for (j = 0; j < N; j = j + 1) begin
                    shifted[j]  = SCALE[i][j] - max_val;   // always ≤ 0
                    exp_val[j]  = exp_lut(shifted[j]);
                    sum_exp     = sum_exp + {32'd0, exp_val[j]};
                end

                // ── STEP 3 : normalise ─────────────────────────
                
                for (j = 0; j < N; j = j + 1) begin
                    if (sum_exp != 64'd0)
                        WEIGHT[i][j] = (exp_val[j] * 32'd256) / sum_exp[31:0];
                    else
                        WEIGHT[i][j] = 32'd0;
                end

            end // for i

            done <= 1'b1;

        end else begin
            done <= 1'b0;
        end

    end 

endmodule

rtl/scaling_unit.v
module scaling_unit #(parameter N=2)(

    input clk,
    input start,

    input signed [31:0] SCORE [0:N-1][0:N-1],

    output reg signed [31:0] SCALE [0:N-1][0:N-1],
    output reg done
);

integer i,j;

always @(posedge clk) begin

    if(start) begin

        for(i=0;i<N;i=i+1) begin

            for(j=0;j<N;j=j+1) begin

                SCALE[i][j] = SCORE[i][j] >>> 1;
            end
        end

        done <= 1;
    end
end

endmodule

rtl/score_unit.v
module score_unit #(parameter N=2, D=4)(

    input clk,
    input start,

    input signed [31:0] Q [0:N-1][0:D-1],
    input signed [31:0] K [0:N-1][0:D-1],

    output reg signed [31:0] SCORE [0:N-1][0:N-1],
    output reg done
);

integer i,j,k;

always @(posedge clk) begin

    if(start) begin

        for(i=0;i<N;i=i+1) begin

            for(j=0;j<N;j=j+1) begin

                SCORE[i][j] = 0;

                for(k=0;k<D;k=k+1) begin

                    SCORE[i][j] =
                        SCORE[i][j] +
                        Q[i][k] * K[j][k];
                end

            end
        end

        done <= 1;
    end
end

endmodule

rtl/matrix_mult.v
module matrix_mult #(parameter N=2, D=4)(
    input clk,
    input start,

    input signed [15:0] A [0:N-1][0:D-1],
    input signed [15:0] B [0:D-1][0:D-1],

    output reg signed [31:0] C [0:N-1][0:D-1],
    output reg done
);

integer i,j,k;

always @(posedge clk) begin

    if(start) begin

        for(i=0;i<N;i=i+1) begin

            for(j=0;j<D;j=j+1) begin

                C[i][j] = 0;

                for(k=0;k<D;k=k+1) begin

                    C[i][j] = C[i][j] + A[i][k] * B[k][j];
                end

            end
        end

        done <= 1;
    end
end

endmodule

rtl/controller_fsm.v
module controller_fsm(

    input clk,
    input rst,

    // done signals from modules
    input load_done,
    input qkv_done,
    input score_done,
    input scale_done,
    input softmax_done,
    input output_done,
    input write_done,

    // control signals to modules
    output reg load_start,
    output reg qkv_start,
    output reg score_start,
    output reg scale_start,
    output reg softmax_start,
    output reg output_start,
    output reg write_start,

    output reg done
);

//
// STATE DEFINITIONS
//

parameter IDLE     = 3'd0;
parameter LOAD     = 3'd1;
parameter GEN_QKV  = 3'd2;
parameter SCORE    = 3'd3;
parameter SCALE    = 3'd4;
parameter SOFTMAX  = 3'd5;
parameter OUTPUT   = 3'd6;
parameter WRITE    = 3'd7;

//
// STATE REGISTERS
//

reg [2:0] current_state;
reg [2:0] next_state;

//
// STATE UPDATE
//

always @(posedge clk or posedge rst) begin

    if(rst)
        current_state <= IDLE;

    else
        current_state <= next_state;

end

//
// NEXT STATE LOGIC
//

always @(*) begin

    next_state = current_state;

    case(current_state)

    //--------------------------------
    IDLE:
    begin
        next_state = LOAD;
    end

    //--------------------------------
    LOAD:
    //--------------------------------
    begin
        if(load_done)
            next_state = GEN_QKV;
    end

    //--------------------------------
    GEN_QKV:
    //--------------------------------
    begin
        if(qkv_done)
            next_state = SCORE;
    end

    //--------------------------------
    SCORE:
    //--------------------------------
    begin
        if(score_done)
            next_state = SCALE;
    end

    //--------------------------------
    SCALE:
    //--------------------------------
    begin
        if(scale_done)
            next_state = SOFTMAX;
    end

    //--------------------------------
    SOFTMAX:
    //--------------------------------
    begin
        if(softmax_done)
            next_state = OUTPUT;
    end

    //--------------------------------
    OUTPUT:
    //--------------------------------
    begin
        if(output_done)
            next_state = WRITE;
    end

    //--------------------------------
    WRITE:
    //--------------------------------
    begin
        //if(write_done)
            //next_state = IDLE;
        

        if(write_done)
            next_state = WRITE;

   
        
    end

    default:
        next_state = IDLE;

endcase
end

//
// OUTPUT CONTROL LOGIC
//

always @(*) begin

    // default outputs

    load_start     = 0;
    qkv_start      = 0;
    score_start    = 0;
    scale_start    = 0;
    softmax_start  = 0;
    output_start   = 0;
    write_start    = 0;

    done           = 0;

    case(current_state)

    //--------------------------------
    // IDLE
    //--------------------------------
    IDLE:
    begin
        done = 0;
    end

    //--------------------------------
    // LOAD
    //--------------------------------
    LOAD:
    begin
        load_start = 1;
    end

    //--------------------------------
    // GEN_QKV
    //--------------------------------
    GEN_QKV:
    begin
        qkv_start = 1;
    end

    //--------------------------------
    // SCORE
    //--------------------------------
    SCORE:
    begin
        score_start = 1;
    end

    //--------------------------------
    // SCALE
    //--------------------------------
    SCALE:
    begin
        scale_start = 1;
    end

    //--------------------------------
    // SOFTMAX
    //--------------------------------
    SOFTMAX:
    begin
        softmax_start = 1;
    end

    //--------------------------------
    // OUTPUT
    //--------------------------------
    OUTPUT:
    begin
        output_start = 1;
    end

    //--------------------------------
    // WRITE
    //--------------------------------
    WRITE:
    begin
        //write_start = 1;
        write_start <= 0;
        @(posedge clk);
        write_start <= 1;
        @(posedge clk);
        write_start <= 0;
        done = 1;
    end

endcase
end

endmodule

rtl/attention_top.v
module attention_top(

    input clk,
    input rst
);

//
// PARAMETERS
//

parameter N = 2;
parameter D = 4;

//
// INPUT MEMORIES
//

reg signed [15:0] X  [0:N-1][0:D-1];

reg signed [15:0] WQ [0:D-1][0:D-1];
reg signed [15:0] WK [0:D-1][0:D-1];
reg signed [15:0] WV [0:D-1][0:D-1];

//
// INTERNAL BUFFERS
//

wire signed [31:0] Q [0:N-1][0:D-1];
wire signed [31:0] K [0:N-1][0:D-1];
wire signed [31:0] V [0:N-1][0:D-1];

wire signed [31:0] SCORE [0:N-1][0:N-1];
wire signed [31:0] SCALE [0:N-1][0:N-1];
wire signed [31:0] WEIGHT [0:N-1][0:N-1];

wire signed [31:0] OUT [0:N-1][0:D-1];

//
// FSM CONTROL SIGNALS
//

wire load_start;
wire qkv_start;
wire score_start;
wire scale_start;
wire softmax_start;
wire output_start;
wire write_start;

wire load_done;
wire qkv_done;
wire score_done;
wire scale_done;
wire softmax_done;
wire output_done;
wire write_done;

wire done;

//
// INTERNAL CONTROL
//

reg finished;

//
// FILE LOADING
//

integer i;
integer j;
integer outfile;

initial begin

    finished = 0;

    //
    // LOAD INPUT TOKENS
    //

    $readmemh("data/token.txt", X);

    //
    // LOAD WEIGHT MATRICES
    //

    $readmemh("data/wq.txt", WQ);
    $readmemh("data/wk.txt", WK);
    $readmemh("data/wv.txt", WV);

end

//
// LOAD DONE
//

assign load_done = 1'b1;

//
// FSM CONTROLLER
//

controller_fsm FSM (

    .clk(clk),
    .rst(rst),

    .load_done(load_done),
    .qkv_done(qkv_done),
    .score_done(score_done),
    .scale_done(scale_done),
    .softmax_done(softmax_done),
    .output_done(output_done),
    .write_done(write_done),

    .load_start(load_start),
    .qkv_start(qkv_start),
    .score_start(score_start),
    .scale_start(scale_start),
    .softmax_start(softmax_start),
    .output_start(output_start),
    .write_start(write_start),

    .done(done)
);

//
// Q GENERATION
//

matrix_mult #(N,D) Q_GEN (
    
    .clk(clk),
    .start(qkv_start),

    .A(X),
    .B(WQ),

    .C(Q),

    .done(qkv_done)
);

//
// K GENERATION
//

matrix_mult #(N,D) K_GEN (

    .clk(clk),
    .start(qkv_start),

    .A(X),
    .B(WK),

    .C(K),

    .done()
);

//
// V GENERATION
//

matrix_mult #(N,D) V_GEN (

    .clk(clk),
    .start(qkv_start),

    .A(X),
    .B(WV),

    .C(V),

    .done()
);

//
// SCORE UNIT
//

score_unit #(N,D) SCORE_UNIT (

    .clk(clk),
    .start(score_start),

    .Q(Q),
    .K(K),

    .SCORE(SCORE),

    .done(score_done)
);

//
// SCALING UNIT
//

scaling_unit #(N) SCALE_UNIT (

    .clk(clk),
    .start(scale_start),

    .SCORE(SCORE),

    .SCALE(SCALE),

    .done(scale_done)
);

//
// SOFTMAX APPROXIMATION
//

softmax_approx #(N) SOFTMAX_UNIT (

    .clk(clk),
    .start(softmax_start),

    .SCALE(SCALE),

    .WEIGHT(WEIGHT),

    .done(softmax_done)
);

//
// FINAL OUTPUT MAC
//

output_mac #(N,D) OUTPUT_UNIT (

    .clk(clk),
    .start(output_start),

    .W(WEIGHT),
    .V(V),

    .OUT(OUT),

    .done(output_done)
);

//
// OUTPUT FILE WRITING + DEBUG
//

always @(posedge clk or posedge rst) begin

    if(rst) begin

        finished <= 0;

    end

    else begin

        if(!finished) begin

            //
            // WRITE OUTPUT FILE
            //

            if(write_start) begin

                outfile = $fopen("output/output.txt","w");

                for(i=0;i<N;i=i+1) begin

                    for(j=0;j<D;j=j+1) begin

                        $fwrite(outfile,"%d ", OUT[i][j]);

                    end

                    $fwrite(outfile,"\n");

                end

                $fclose(outfile);

                finished <= 1;

            end

            //
            // DISPLAY Q/K/V
            //

            if(qkv_done) begin

                $display("\n========== Q MATRIX ==========");

                for(i=0;i<N;i=i+1) begin
                    for(j=0;j<D;j=j+1) begin

                        $display("Q[%0d][%0d] = %0d",
                                  i,j,Q[i][j]);

                    end
                end

                $display("\n========== K MATRIX ==========");

                for(i=0;i<N;i=i+1) begin
                    for(j=0;j<D;j=j+1) begin

                        $display("K[%0d][%0d] = %0d",
                                  i,j,K[i][j]);

                    end
                end

                $display("\n========== V MATRIX ==========");

                for(i=0;i<N;i=i+1) begin
                    for(j=0;j<D;j=j+1) begin

                        $display("V[%0d][%0d] = %0d",
                                  i,j,V[i][j]);

                    end
                end

            end

            //
            // DISPLAY SCORE
            //

            if(score_done) begin

                $display("\n========== SCORE MATRIX ==========");

                for(i=0;i<N;i=i+1) begin
                    for(j=0;j<N;j=j+1) begin

                        $display("SCORE[%0d][%0d] = %0d",
                                  i,j,SCORE[i][j]);

                    end
                end

            end

            //
            // DISPLAY SCALE
            //

            if(scale_done) begin

                $display("\n========== SCALE MATRIX ==========");

                for(i=0;i<N;i=i+1) begin
                    for(j=0;j<N;j=j+1) begin

                        $display("SCALE[%0d][%0d] = %0d",
                                  i,j,SCALE[i][j]);

                    end
                end

            end

            //
            // DISPLAY WEIGHTS
            //

            if(softmax_done) begin

                $display("\n========== SOFTMAX WEIGHTS ==========");

                for(i=0;i<N;i=i+1) begin
                    for(j=0;j<N;j=j+1) begin

                        $display("WEIGHT[%0d][%0d] = %0d",
                                  i,j,WEIGHT[i][j]);

                    end
                end

            end

            //
            // DISPLAY FINAL OUTPUT
            //

            if(output_done) begin

                $display("\n========== FINAL OUTPUT ==========");

                for(i=0;i<N;i=i+1) begin
                    for(j=0;j<D;j=j+1) begin

                        $display("OUT[%0d][%0d] = %0d",
                                  i,j,OUT[i][j]);

                    end
                end

            end

        end

    end

end

//
// WRITE DONE
//

assign write_done = write_start;

endmodule

tb/tb_attention.v
module tb_attention;

reg clk;
reg rst;

attention_top dut(
    .clk(clk),
    .rst(rst)
);

always #5 clk = ~clk;

initial begin

    clk = 0;
    rst = 1;

    #20;
    rst = 0;

    #1000;

    $finish;
end

initial begin

    $dumpfile("output/attention.vcd");
    $dumpvars(0,tb_attention);

end

endmodule

output/attention.vcd
$date
	Sun May 24 02:05:46 2026
$end
$version
	Icarus Verilog
$end
$timescale
	1ps
$end
$scope module tb_attention $end
$var reg 1 ! clk $end
$var reg 1 " rst $end
$scope module dut $end
$var wire 1 ! clk $end
$var wire 1 # load_done $end
$var wire 1 " rst $end
$var wire 1 $ write_done $end
$var wire 1 % write_start $end
$var wire 1 & softmax_start $end
$var wire 1 ' softmax_done $end
$var wire 1 ( score_start $end
$var wire 1 ) score_done $end
$var wire 1 * scale_start $end
$var wire 1 + scale_done $end
$var wire 1 , qkv_start $end
$var wire 1 - qkv_done $end
$var wire 1 . output_start $end
$var wire 1 / output_done $end
$var wire 1 0 load_start $end
$var wire 1 1 done $end
$var parameter 32 2 D $end
$var parameter 32 3 N $end
$var reg 1 4 finished $end
$var integer 32 5 i [31:0] $end
$var integer 32 6 j [31:0] $end
$var integer 32 7 outfile [31:0] $end
$scope module FSM $end
$var wire 1 ! clk $end
$var wire 1 # load_done $end
$var wire 1 " rst $end
$var wire 1 $ write_done $end
$var wire 1 ' softmax_done $end
$var wire 1 ) score_done $end
$var wire 1 + scale_done $end
$var wire 1 - qkv_done $end
$var wire 1 / output_done $end
$var parameter 3 8 GEN_QKV $end
$var parameter 3 9 IDLE $end
$var parameter 3 : LOAD $end
$var parameter 3 ; OUTPUT $end
$var parameter 3 < SCALE $end
$var parameter 3 = SCORE $end
$var parameter 3 > SOFTMAX $end
$var parameter 3 ? WRITE $end
$var reg 3 @ current_state [2:0] $end
$var reg 1 1 done $end
$var reg 1 0 load_start $end
$var reg 3 A next_state [2:0] $end
$var reg 1 . output_start $end
$var reg 1 , qkv_start $end
$var reg 1 * scale_start $end
$var reg 1 ( score_start $end
$var reg 1 & softmax_start $end
$var reg 1 % write_start $end
$upscope $end
$scope module K_GEN $end
$var wire 1 ! clk $end
$var wire 1 , start $end
$var parameter 32 B D $end
$var parameter 32 C N $end
$var reg 1 D done $end
$var integer 32 E i [31:0] $end
$var integer 32 F j [31:0] $end
$var integer 32 G k [31:0] $end
$upscope $end
$scope module OUTPUT_UNIT $end
$var wire 1 ! clk $end
$var wire 1 . start $end
$var parameter 32 H D $end
$var parameter 32 I N $end
$var reg 64 J acc [63:0] $end
$var reg 1 / done $end
$var integer 32 K i [31:0] $end
$var integer 32 L j [31:0] $end
$var integer 32 M k [31:0] $end
$upscope $end
$scope module Q_GEN $end
$var wire 1 ! clk $end
$var wire 1 , start $end
$var parameter 32 N D $end
$var parameter 32 O N $end
$var reg 1 - done $end
$var integer 32 P i [31:0] $end
$var integer 32 Q j [31:0] $end
$var integer 32 R k [31:0] $end
$upscope $end
$scope module SCALE_UNIT $end
$var wire 1 ! clk $end
$var wire 1 * start $end
$var parameter 32 S N $end
$var reg 1 + done $end
$var integer 32 T i [31:0] $end
$var integer 32 U j [31:0] $end
$upscope $end
$scope module SCORE_UNIT $end
$var wire 1 ! clk $end
$var wire 1 ( start $end
$var parameter 32 V D $end
$var parameter 32 W N $end
$var reg 1 ) done $end
$var integer 32 X i [31:0] $end
$var integer 32 Y j [31:0] $end
$var integer 32 Z k [31:0] $end
$upscope $end
$scope module SOFTMAX_UNIT $end
$var wire 1 ! clk $end
$var wire 1 & start $end
$var parameter 32 [ N $end
$var reg 1 ' done $end
$var reg 32 \ max_val [31:0] $end
$var reg 64 ] sum_exp [63:0] $end
$var integer 32 ^ i [31:0] $end
$var integer 32 _ j [31:0] $end
$scope function exp_lut $end
$var reg 32 ` abs_x [31:0] $end
$var reg 32 a x [31:0] $end
$upscope $end
$upscope $end
$scope module V_GEN $end
$var wire 1 ! clk $end
$var wire 1 , start $end
$var parameter 32 b D $end
$var parameter 32 c N $end
$var reg 1 d done $end
$var integer 32 e i [31:0] $end
$var integer 32 f j [31:0] $end
$var integer 32 g k [31:0] $end
$upscope $end
$upscope $end
$upscope $end
$enddefinitions $end
$comment Show the parameter values. $end
$dumpall
b10 c
b100 b
b10 [
b10 W
b100 V
b10 S
b10 O
b100 N
b10 I
b100 H
b10 C
b100 B
b111 ?
b101 >
b11 =
b100 <
b110 ;
b1 :
b0 9
b10 8
b10 3
b100 2
$end
#0
$dumpvars
bx g
bx f
bx e
xd
bx a
bx `
bx _
bx ^
bx ]
bx \
bx Z
bx Y
bx X
bx U
bx T
bx R
bx Q
bx P
bx M
bx L
bx K
bx J
bx G
bx F
bx E
xD
b1 A
b0 @
bx 7
bx 6
bx 5
04
01
00
x/
0.
x-
0,
x+
0*
x)
0(
x'
0&
0%
0$
1#
1"
0!
$end
#5000
b1 A
0'
0/
1!
#10000
0!
#15000
1!
#20000
0!
0"
#25000
10
b10 A
b1 @
1!
#30000
0!
#35000
1,
00
b10 @
1!
#40000
0!
#45000
b11 A
1-
1D
1d
b100 R
b100 Q
b10 P
b100 G
b100 F
b10 E
b100 g
b100 f
b10 e
1!
#50000
0!
#55000
1(
0,
b11 @
b100 g
b100 f
b10 e
b100 G
b100 F
b10 E
b100 R
b100 Q
b10 P
b100 6
b10 5
1!
#60000
0!
#65000
b100 A
1)
b100 Z
b10 Y
b10 X
b100 6
b10 5
1!
#70000
0!
#75000
1*
0(
b100 @
b100 Z
b10 Y
b10 X
b10 6
b10 5
1!
#80000
0!
#85000
b101 A
1+
b10 U
b10 T
b10 6
b10 5
1!
#90000
0!
#95000
1&
0*
b101 @
b10 U
b10 T
b10 6
b10 5
1!
#100000
0!
#105000
b110 A
1'
b110100 `
b0 a
b100000000 ]
b10 _
b1010111 \
b10 ^
b10 6
b10 5
1!
#110000
0!
#115000
1.
0&
b110 @
b110100 `
b0 a
b100000000 ]
b10 _
b1010111 \
b10 ^
b10 6
b10 5
1!
#120000
0!
#125000
b111 A
0'
1/
b10 M
b100000000000 J
b100 L
b10 K
b10 6
b10 5
1!
#130000
0!
#135000
0.
b111 @
b10 M
b100000000000 J
b100 L
b10 K
b100 6
b10 5
1!
#140000
0!
#145000
0/
1$
1%
b100 6
b10 5
1!
#150000
0!
#155000
0$
0%
14
11
b10 6
b10 5
b10000000000000000000000000000011 7
1!
